ezmysqlpy/__init__.py
ezmysqlpy/dbops.py
ezmysqlpy/exceptions.py
ezmysqlpy-1.0.0.dist-info/METADATA
ezmysqlpy-1.0.0.dist-info/WHEEL
ezmysqlpy-1.0.0.dist-info/licenses/LICENSE
ezmysqlpy-1.0.0.dist-info/RECORD
