Metadata-Version: 2.1
Name: ezmysqlpy
Version: 1.0.0
Summary: A package that simplifies most common MySQL database operations.
Project-URL: Homepage, https://github.com/sahanLK/ezmysqlpy
Project-URL: Bug Tracker, https://github.com/sahanLK/ezmysqlpy/issues
Author-email: Sahan Lakshitha <sahanlksk@gmail.com>
License: MIT
Classifier: Intended Audience :: Developers
Classifier: License :: OSI Approved :: MIT License
Classifier: Operating System :: OS Independent
Classifier: Programming Language :: Python :: 3
Classifier: Topic :: Database
Requires-Python: >=3.5
